README.md
setup.py
reclaim/__init__.py
reclaim/reclaimClient.py
reclaim.py.egg-info/PKG-INFO
reclaim.py.egg-info/SOURCES.txt
reclaim.py.egg-info/dependency_links.txt
reclaim.py.egg-info/requires.txt
reclaim.py.egg-info/top_level.txt