Metadata-Version: 2.1
Name: reclaim.py
Version: 0.1
Summary: Unofficial reclaim.ai Python Library for creating tasks which go into reclaim.ai
Home-page: https://github.com/lars-re/reclaim.py
Author: Lars
Author-email: 45080708+lars-re@users.noreply.github.com
License: MIT
Platform: UNKNOWN
